{
  "total": 6095,
  "ip_based": 4018,
  "domain_based": 2036,
  "by_country": {
    "DE": 494,
    "DOMAIN": 2036,
    "TR": 36,
    "UNKNOWN": 390,
    "HK": 58,
    "NL": 210,
    "US": 335,
    "SG": 46,
    "GB": 236,
    "IR": 93,
    "TH": 7,
    "FR": 188,
    "CA": 154,
    "SC": 13,
    "IN": 32,
    "AE": 55,
    "MD": 60,
    "RU": 692,
    "LV": 20,
    "MY": 13,
    "UA": 11,
    "CY": 38,
    "CZ": 8,
    "CH": 8,
    "LT": 39,
    "LU": 3,
    "FI": 80,
    "SE": 51,
    "JP": 80,
    "PL": 164,
    "BE": 3,
    "AT": 13,
    "BR": 19,
    "IT": 17,
    "CN": 4,
    "ES": 5,
    "KZ": 29,
    "AL": 1,
    "AU": 12,
    "ZA": 2,
    "BG": 6,
    "RO": 6,
    "KR": 6,
    "SK": 2,
    "MH": 2,
    "PK": 9,
    "AM": 9,
    "EE": 22,
    "IE": 4,
    "KE": 1,
    "SA": 13,
    "HU": 21,
    "NO": 7,
    "IM": 4,
    "MT": 4,
    "MU": 1,
    "JO": 8,
    "UZ": 1,
    "AR": 8,
    "NZ": 3,
    "IS": 4,
    "OM": 1,
    "VN": 84,
    "MK": 5,
    "MX": 6,
    "PT": 4,
    "AZ": 1,
    "SI": 4,
    "CL": 1,
    "IL": 10,
    "KW": 7,
    "GR": 11,
    "EG": 7,
    "KH": 4,
    "NG": 1,
    "PE": 1,
    "PR": 2,
    "MA": 1,
    "EC": 2,
    "CO": 2,
    "TW": 3,
    "ID": 1
  },
  "by_protocol": {
    "vless": 4253,
    "vmess": 599,
    "trojan": 248,
    "ss": 809,
    "hysteria": 144,
    "wireguard": 1
  }
}